{"lastUsed":1675608700123,"path":"D:\/Spring-Personal","projectCount":1,"recentFiles":[{"path":"\/bus-reservation\/src\/main\/resources","parentWorkspace":"D:\/Spring-Personal","name":"application.properties","lastModified":1675237674602,"locationURI":"file:\/D:\/Spring-Personal\/bus-reservation\/src\/main\/resources\/application.properties"},{"path":"\/bus-reservation\/src\/main\/java\/com\/busreservation\/entity","parentWorkspace":"D:\/Spring-Personal","name":"Reservation.java","lastModified":1675608383812,"locationURI":"file:\/D:\/Spring-Personal\/bus-reservation\/src\/main\/java\/com\/busreservation\/entity\/Reservation.java"},{"path":"\/bus-reservation\/src\/main\/java\/com\/busreservation\/dto","parentWorkspace":"D:\/Spring-Personal","name":"BusDto.java","lastModified":1675608500881,"locationURI":"file:\/D:\/Spring-Personal\/bus-reservation\/src\/main\/java\/com\/busreservation\/dto\/BusDto.java"},{"path":"\/bus-reservation\/src\/main\/resources\/templates\/reservation","parentWorkspace":"D:\/Spring-Personal","name":"cancel.html","lastModified":1675496980041,"locationURI":"file:\/D:\/Spring-Personal\/bus-reservation\/src\/main\/resources\/templates\/reservation\/cancel.html"},{"path":"\/bus-reservation\/src\/main\/resources\/templates\/login","parentWorkspace":"D:\/Spring-Personal","name":"login.html","lastModified":1675390669999,"locationURI":"file:\/D:\/Spring-Personal\/bus-reservation\/src\/main\/resources\/templates\/login\/login.html"},{"path":"\/bus-reservation\/src\/main\/resources\/templates\/reservation","parentWorkspace":"D:\/Spring-Personal","name":"seat.html","lastModified":1675326879007,"locationURI":"file:\/D:\/Spring-Personal\/bus-reservation\/src\/main\/resources\/templates\/reservation\/seat.html"},{"path":"\/bus-reservation\/src\/main\/resources\/templates\/reservation","parentWorkspace":"D:\/Spring-Personal","name":"lookup.html","lastModified":1675416582664,"locationURI":"file:\/D:\/Spring-Personal\/bus-reservation\/src\/main\/resources\/templates\/reservation\/lookup.html"},{"path":"\/bus-reservation\/src\/main\/java\/com\/busreservation\/entity","parentWorkspace":"D:\/Spring-Personal","name":"Seat.java","lastModified":1675608404791,"locationURI":"file:\/D:\/Spring-Personal\/bus-reservation\/src\/main\/java\/com\/busreservation\/entity\/Seat.java"},{"path":"\/bus-reservation\/src\/main\/resources\/templates\/reservation","parentWorkspace":"D:\/Spring-Personal","name":"check.html","lastModified":1675410477332,"locationURI":"file:\/D:\/Spring-Personal\/bus-reservation\/src\/main\/resources\/templates\/reservation\/check.html"},{"path":"\/bus-reservation\/src\/main\/resources\/templates\/fragments","parentWorkspace":"D:\/Spring-Personal","name":"sidebar.html","lastModified":1675410389002,"locationURI":"file:\/D:\/Spring-Personal\/bus-reservation\/src\/main\/resources\/templates\/fragments\/sidebar.html"},{"path":"\/bus-reservation\/src\/main\/java\/com\/busreservation\/entity","parentWorkspace":"D:\/Spring-Personal","name":"Customer.java","lastModified":1675608230567,"locationURI":"file:\/D:\/Spring-Personal\/bus-reservation\/src\/main\/java\/com\/busreservation\/entity\/Customer.java"},{"path":"\/bus-reservation\/src\/main\/resources\/templates\/login","parentWorkspace":"D:\/Spring-Personal","name":"join.html","lastModified":1675395442933,"locationURI":"file:\/D:\/Spring-Personal\/bus-reservation\/src\/main\/resources\/templates\/login\/join.html"},{"path":"\/bus-reservation\/src\/main\/java\/com\/busreservation\/dto","parentWorkspace":"D:\/Spring-Personal","name":"SeatDto.java","lastModified":1675608715070,"locationURI":"file:\/D:\/Spring-Personal\/bus-reservation\/src\/main\/java\/com\/busreservation\/dto\/SeatDto.java"},{"path":"\/bus-reservation\/src\/main\/java\/com\/busreservation\/entity","parentWorkspace":"D:\/Spring-Personal","name":"Bus.java","lastModified":1675608116217,"locationURI":"file:\/D:\/Spring-Personal\/bus-reservation\/src\/main\/java\/com\/busreservation\/entity\/Bus.java"},{"path":"\/bus-reservation\/src\/main\/java\/com\/busreservation","parentWorkspace":"D:\/Spring-Personal","name":"BusReservationApplication.java","lastModified":1675595190074,"locationURI":"file:\/D:\/Spring-Personal\/bus-reservation\/src\/main\/java\/com\/busreservation\/BusReservationApplication.java"},{"path":"\/bus-reservation\/src\/main\/java\/bus\/busreservation\/constant","parentWorkspace":"D:\/Spring-Personal","name":"Role.java","lastModified":1675607116732,"locationURI":"file:\/D:\/Spring-Personal\/bus-reservation\/src\/main\/java\/bus\/busreservation\/constant\/Role.java"},{"path":"\/bus-reservation\/src\/main\/resources\/templates\/sample","parentWorkspace":"D:\/Spring-Personal","name":"sample.html","lastModified":1675239517095,"locationURI":"file:\/D:\/Spring-Personal\/bus-reservation\/src\/main\/resources\/templates\/sample\/sample.html"},{"path":"\/bus-reservation\/src\/main\/java\/com\/busreservation\/entity","parentWorkspace":"D:\/Spring-Personal","name":"Path.java","lastModified":1675608700124,"locationURI":"file:\/D:\/Spring-Personal\/bus-reservation\/src\/main\/java\/com\/busreservation\/entity\/Path.java"},{"path":"\/bus-reservation\/src\/main\/java\/com\/busreservation\/controller","parentWorkspace":"D:\/Spring-Personal","name":"ReservationController.java","lastModified":1675497775940,"locationURI":"file:\/D:\/Spring-Personal\/bus-reservation\/src\/main\/java\/com\/busreservation\/controller\/ReservationController.java"},{"path":"\/bus-reservation\/src\/main\/resources\/templates","parentWorkspace":"D:\/Spring-Personal","name":"main.html","lastModified":1675411913372,"locationURI":"file:\/D:\/Spring-Personal\/bus-reservation\/src\/main\/resources\/templates\/main.html"},{"path":"\/bus-reservation\/src\/main\/resources\/templates\/edit","parentWorkspace":"D:\/Spring-Personal","name":"edit.html","lastModified":1675604000191,"locationURI":"file:\/D:\/Spring-Personal\/bus-reservation\/src\/main\/resources\/templates\/edit\/edit.html"},{"path":"\/bus-reservation\/src\/main\/java\/com\/busreservation\/dto","parentWorkspace":"D:\/Spring-Personal","name":"PathDto.java","lastModified":1675608656426,"locationURI":"file:\/D:\/Spring-Personal\/bus-reservation\/src\/main\/java\/com\/busreservation\/dto\/PathDto.java"},{"path":"\/bus-reservation","parentWorkspace":"D:\/Spring-Personal","name":"pom.xml","lastModified":1675127961349,"locationURI":"file:\/D:\/Spring-Personal\/bus-reservation\/pom.xml"},{"path":"\/bus-reservation\/src\/main\/resources\/templates\/edit","parentWorkspace":"D:\/Spring-Personal","name":"edit_input.html","lastModified":1675603662919,"locationURI":"file:\/D:\/Spring-Personal\/bus-reservation\/src\/main\/resources\/templates\/edit\/edit_input.html"},{"path":"\/bus-reservation\/src\/main\/resources\/static\/css","parentWorkspace":"D:\/Spring-Personal","name":"all.css","lastModified":1675603996933,"locationURI":"file:\/D:\/Spring-Personal\/bus-reservation\/src\/main\/resources\/static\/css\/all.css"},{"path":"\/bus-reservation\/src\/main\/java\/com\/busreservation\/dto","parentWorkspace":"D:\/Spring-Personal","name":"CustomerDto.java","lastModified":1675608635659,"locationURI":"file:\/D:\/Spring-Personal\/bus-reservation\/src\/main\/java\/com\/busreservation\/dto\/CustomerDto.java"},{"path":"\/bus-reservation\/src\/main\/java\/com\/busreservation\/dto","parentWorkspace":"D:\/Spring-Personal","name":"ReservationDto.java","lastModified":1675608679527,"locationURI":"file:\/D:\/Spring-Personal\/bus-reservation\/src\/main\/java\/com\/busreservation\/dto\/ReservationDto.java"}]}